{
    "id": "10790",
    "url": "https://songlib.com/sets/4297/10790/",
    "title": "Retiro de Homens - Sábado de manhã (Geraldo)",
    "notes": "",
    "date": "24/08/2024",
    "leader": "",
    "is_draft": false,
    "songs": [
        {
            "song_id": 85651,
            "no": "1",
            "key": "E",
            "use_b": false,
            "notes": ""
        },
        {
            "song_id": 85397,
            "no": "2",
            "key": "C",
            "use_b": false,
            "notes": ""
        },
        {
            "song_id": 85652,
            "no": "3",
            "key": "A",
            "use_b": false,
            "notes": ""
        },
        {
            "song_id": 85654,
            "no": "4",
            "key": "D",
            "use_b": false,
            "notes": "Retorno\ndo \"Break\""
        }
    ]
}