{
    "id": "10856",
    "url": "https://songlib.com/sets/4297/10856/",
    "title": "Banda 3 - Geraldo",
    "notes": "",
    "date": "08/09/2024",
    "leader": "",
    "is_draft": false,
    "songs": [
        {
            "song_id": 87065,
            "no": "1",
            "key": "G",
            "use_b": false,
            "notes": ""
        },
        {
            "song_id": 87066,
            "no": "2",
            "key": "C",
            "use_b": false,
            "notes": ""
        },
        {
            "song_id": 85745,
            "no": "3",
            "key": "A (-1)",
            "use_b": false,
            "notes": ""
        },
        {
            "song_id": 87067,
            "no": "4",
            "key": "D",
            "use_b": false,
            "notes": "Oferta"
        },
        {
            "song_id": 87068,
            "no": "5",
            "key": "E",
            "use_b": false,
            "notes": ""
        },
        {
            "song_id": 87069,
            "no": "6",
            "key": "D",
            "use_b": false,
            "notes": ""
        }
    ]
}