{
    "id": "11061",
    "url": "https://songlib.com/sets/4297/11061/",
    "title": "Banda 1 - Theo",
    "notes": "",
    "date": "20/10/2024",
    "leader": "",
    "is_draft": false,
    "songs": [
        {
            "song_id": 85273,
            "no": "1",
            "key": "E",
            "use_b": false,
            "notes": ""
        },
        {
            "song_id": 85077,
            "no": "2",
            "key": "E",
            "use_b": false,
            "notes": ""
        },
        {
            "song_id": 87935,
            "no": "3",
            "key": "C",
            "use_b": false,
            "notes": ""
        },
        {
            "song_id": 87490,
            "no": "4",
            "key": "C",
            "use_b": false,
            "notes": "Oferta"
        },
        {
            "song_id": 87936,
            "no": "5",
            "key": "A (+2)",
            "use_b": false,
            "notes": ""
        },
        {
            "song_id": 85403,
            "no": "6",
            "key": "Bb",
            "use_b": true,
            "notes": ""
        }
    ]
}