{
    "id": "11318",
    "url": "https://songlib.com/sets/4297/11318/",
    "title": "Banda 2 - Pompeu",
    "notes": "",
    "date": "29/12/2024",
    "leader": "",
    "is_draft": false,
    "songs": [
        {
            "song_id": 87491,
            "no": "1",
            "key": "D",
            "use_b": false,
            "notes": ""
        },
        {
            "song_id": 85400,
            "no": "2",
            "key": "D",
            "use_b": false,
            "notes": ""
        },
        {
            "song_id": 85656,
            "no": "3",
            "key": "D",
            "use_b": false,
            "notes": ""
        },
        {
            "song_id": 91400,
            "no": "4",
            "key": "C",
            "use_b": false,
            "notes": ""
        },
        {
            "song_id": 87476,
            "no": "5",
            "key": "C",
            "use_b": false,
            "notes": ""
        },
        {
            "song_id": 91493,
            "no": "6",
            "key": "C",
            "use_b": false,
            "notes": ""
        }
    ]
}