{
    "songlib_url": "https://songlib.com/songs/4297/87342/",
    "id": "87342",
    "title": "Saudai o Nome de Jesus (HCC 56)",
    "author": "Hin치rio para o Culto Crist칚o (HCC)",
    "notes": "",
    "year": "",
    "key": "G",
    "ccli": "",
    "copyright": "",
    "time_sig": "3/4",
    "tempo": "",
    "feel": "",
    "theme": "",
    "tags": "",
    "url": "https://www.youtube.com/watch?v=5tCSPGyFGVE",
    "chord_chart": "[Intro]\n(Coro)\n\n[1춹 Estrofe]\n.G      D  G  Em  C  D7  G \n Saudai o  no_me  de Je_sus. Arcanjos, vos prostrai\n.G/B  C      G/D  D7   G\n Ar - canjos, vos prostrais\n.        B7  Em  C  D7  G\n O Filho do  glorio_so Deus\n\n[Coro]\n.     C6 | G | D7 | G      \n Com gl칩 ___________ ria\n. C6      D       G              C  G/D   D   G\n Gl칩ria, gl칩ria, gl칩ria, com gl칩ria co___ro__ai\n\n[2춹 Estrofe]\n.G    D  G  Em  C  D7  G \n 칍 esco_lhi_da  ge_ra_칞칚o. Do bom, eterno pai\n.G/B  C     G/D  D7   G\n Do  bom, e_ter__no  pai\n.           B7  Em  C  D7  G\n O grande autor da  salva_칞칚o\n \n[Coro...]\n\n[3춹 Estrofe]\n.G     D  G  Em  C   D7  G \n 칍 perdo__a__dos por Je_sus. Alegres adorai\n.G/B  C     G/D  D7   G\n A___legres a____do__rai\n.          B7   Em  C   D7  G\n O Deus de paz, o  Deus de luz\n \n[Coro...]\n\n[Interl칰dio - (Gl칩ria, Gl칩ria)]\n                        洧           洧륲n. C6  |  D  |  G  |  G  C  |  G/D  D  |  G  |\n\n[4춹 Estrofe]\n.G     D    G  Em  C  D7  G \n 칍 tribos, ra__칞as e  na_칞칫es. Ao rei divino honrai\n.G/B  C     G/D  D7     G\n Ao  rei di_vi___no honrai\n.            B7  Em  C   D7   G\n A quem que_brou os  vis gri_lh칫es\n \n[Coro...]"
}